punjabi_stopwords.py
punjabi_stopwords-1.0.0.dist-info/LICENSE.txt
punjabi_stopwords-1.0.0.dist-info/METADATA
punjabi_stopwords-1.0.0.dist-info/WHEEL
punjabi_stopwords-1.0.0.dist-info/top_level.txt
punjabi_stopwords-1.0.0.dist-info/RECORD
