Metadata-Version: 2.1
Name: punjabi-stopwords
Version: 1.0.0
Summary: A Python library for Punjabi language stopwords.
Home-page: https://github.com/gurpejsingh13/Punjabi_Stopwords.git
Author: Gurpej Singh
Author-email: gurpejsingh462@gmail.com
License: MIT
Keywords: stopwords,punjabi,nlp,punjabi language,natural language processing
Platform: UNKNOWN
Classifier: Development Status :: 5 - Production/Stable
Classifier: Intended Audience :: Developers
Classifier: Topic :: Software Development :: Libraries :: Python Modules
Classifier: License :: OSI Approved :: MIT License
Classifier: Programming Language :: Python :: 3
Classifier: Programming Language :: Python :: 3.7
Classifier: Programming Language :: Python :: 3.8
Classifier: Programming Language :: Python :: 3.9
Classifier: Programming Language :: Python :: 3.10
Requires-Python: >=3.7
